MANIFEST.in
README.txt
setup.cfg
setup.py
docs/HISTORY.txt
horae/__init__.py
horae.resources.egg-info/PKG-INFO
horae.resources.egg-info/SOURCES.txt
horae.resources.egg-info/dependency_links.txt
horae.resources.egg-info/entry_points.txt
horae.resources.egg-info/namespace_packages.txt
horae.resources.egg-info/not-zip-safe
horae.resources.egg-info/requires.txt
horae.resources.egg-info/top_level.txt
horae/resources/__init__.py
horae/resources/configure.zcml
horae/resources/extenders.py
horae/resources/interfaces.py
horae/resources/properties.py
horae/resources/resources.py
horae/resources/utils.py
horae/resources/views.py
horae/resources/vocabulary.py
horae/resources/locales/horae.resources.pot
horae/resources/locales/de/LC_MESSAGES/horae.resources.mo
horae/resources/locales/de/LC_MESSAGES/horae.resources.po